atrium_shell/atrium_shell.py
nuxeolib/__init__.py
nuxeolib/atrium_configure.py
nuxeolib/core_session.py
nuxeolib/encoding.py
nuxeolib/error.py
nuxeolib/model.py
nuxeolib/requests.py
nuxeolib/session.py
nuxeolib/tools.py
nuxeolib/version.py
atrium_tools-4.3.3.dist-info/METADATA
atrium_tools-4.3.3.dist-info/WHEEL
atrium_tools-4.3.3.dist-info/top_level.txt
atrium_tools-4.3.3.dist-info/RECORD
