Metadata-Version: 2.1
Name: atrium-tools
Version: 4.3.3
Summary: Atrium utilities
Home-page: https://atrium.in2p3.fr/
Author: Chris Arnault
Author-email: arnault@lal.in2p3.fr
License: UNKNOWN
Platform: UNKNOWN
Classifier: Programming Language :: Python :: 3.7
Classifier: License :: OSI Approved :: CEA CNRS Inria Logiciel Libre License, version 2.1 (CeCILL-2.1)
